pinnacle_link/__init__.py
pinnacle_link/sdk.py
pinnacle_link/hooks/__init__.py
pinnacle_link/hooks/hook.py
pinnacle_link/models/__init__.py
pinnacle_link/models/base.py
pinnacle_link/models/cancellation_reason.py
pinnacle_link/models/cancellation_reason_details_type.py
pinnacle_link/models/cancellation_reason_response.py
pinnacle_link/models/cancellation_reason_type.py
pinnacle_link/models/currency.py
pinnacle_link/models/fixture.py
pinnacle_link/models/fixtures_league.py
pinnacle_link/models/fixtures_response.py
pinnacle_link/models/in_running_event.py
pinnacle_link/models/in_running_league.py
pinnacle_link/models/in_running_response.py
pinnacle_link/models/in_running_sport.py
pinnacle_link/models/league.py
pinnacle_link/models/leagues.py
pinnacle_link/models/line_response.py
pinnacle_link/models/line_special_v1_get_odds_format.py
pinnacle_link/models/line_straight_v1_get_bet_type.py
pinnacle_link/models/line_straight_v1_get_odds_format.py
pinnacle_link/models/line_straight_v1_get_side.py
pinnacle_link/models/line_straight_v1_get_team.py
pinnacle_link/models/lines_request_teaser.py
pinnacle_link/models/odds_event.py
pinnacle_link/models/odds_league.py
pinnacle_link/models/odds_moneyline.py
pinnacle_link/models/odds_period.py
pinnacle_link/models/odds_response.py
pinnacle_link/models/odds_special_v1_get_odds_format.py
pinnacle_link/models/odds_spread.py
pinnacle_link/models/odds_straight_v1_get_odds_format.py
pinnacle_link/models/odds_team_total.py
pinnacle_link/models/odds_team_totals.py
pinnacle_link/models/odds_total.py
pinnacle_link/models/parlay_line_leg.py
pinnacle_link/models/parlay_line_request.py
pinnacle_link/models/parlay_lines_request.py
pinnacle_link/models/parlay_lines_response_v2.py
pinnacle_link/models/round_robin_option_with_odds_v2.py
pinnacle_link/models/settled_contestants.py
pinnacle_link/models/settled_fixtures_event.py
pinnacle_link/models/settled_fixtures_league.py
pinnacle_link/models/settled_fixtures_period.py
pinnacle_link_client-1.0.1.dist-info/METADATA
pinnacle_link_client-1.0.1.dist-info/WHEEL
pinnacle_link_client-1.0.1.dist-info/top_level.txt
pinnacle_link_client-1.0.1.dist-info/RECORD
