Metadata-Version: 2.1
Name: pinnacle-link-client
Version: 1.0.1
Summary: All about odds and fixtures  # Authentication  Please note that API has restriction that client password can be maximum up 10 characters long.  API uses HTTP Basic access authentication. You need to send Authorization HTTP Request header:    `Authorization: Basic `  Example:  `Authorization: Basic U03MyOT23YbzMDc6d3c3O1DQ1` 
Requires-Python: >=3.7
Requires-Dist: requests >=2.31.0
